README.txt
setup.py
temp_dir.py
test_temp_dir.py
temp_dir.egg-info/PKG-INFO
temp_dir.egg-info/SOURCES.txt
temp_dir.egg-info/dependency_links.txt
temp_dir.egg-info/top_level.txt