Metadata-Version: 1.0
Name: temp-dir
Version: 0.1.1
Summary: Execute block of code within a temporary directory
Home-page: https://github.com/krisztianfekete/temp_dir
Author: Krisztián Fekete
Author-email: fkr972+temp_dir@gmail.com
License: MIT License
Platform: UNKNOWN
Classifier: Intended Audience :: Developers
Classifier: Development Status :: 4 - Beta
Classifier: License :: OSI Approved :: MIT License
Classifier: Programming Language :: Python :: 2.7
Classifier: Programming Language :: Python :: 3
Classifier: Topic :: Software Development :: Libraries
Classifier: Topic :: Software Development :: Testing
